[
    {
        "fechaCompra": "2025-07-01T01:07:47",
        "estadoCompra": true,
        "correoUsuario": "Jheromscript@gmail.com",
        "codigoCompra": "CDC000001",
        "contenidoComprado": [
            {
                "artistas": "Twenty One Pilots",
                "precio": 0,
                "tipoMultimedia": "Cancion",
                "formato": "Digital",
                "generos": "Generos default",
                "titulo": "Overcompensate",
                "duracion": 0,
                "selloDiscografico": "Fueled by Ramen",
                "urlCancion": "https://poomsc.blob.core.windows.net/canciones/01%20-%20Overcompensate.mp3",
                "urlPortada": "https://preview.redd.it/clancy-decals-at-school-v0-rxejcn71c11d1.jpg?width=320&format=pjpg&auto=webp&s=9282940783035a0d13036f235453368382f43af2",
                "anio": 2000,
                "edicion": "Original"
            },
            {
                "artistas": "Twenty One Pilots",
                "precio": 0,
                "tipoMultimedia": "Cancion",
                "formato": "Digital",
                "generos": "Generos default",
                "titulo": "Next Semester",
                "duracion": 0,
                "selloDiscografico": "Fueled by Ramen",
                "urlCancion": "https://poomsc.blob.core.windows.net/canciones/02%20-%20Next%20Semester.mp3",
                "urlPortada": "https://preview.redd.it/clancy-decals-at-school-v0-rxejcn71c11d1.jpg?width=320&format=pjpg&auto=webp&s=9282940783035a0d13036f235453368382f43af2",
                "anio": 2000,
                "edicion": "Original"
            },
            {
                "artistas": "Twenty One Pilots",
                "precio": 0,
                "tipoMultimedia": "Cancion",
                "formato": "Digital",
                "generos": "Generos default",
                "titulo": "Midwest Indigo",
                "duracion": 0,
                "selloDiscografico": "Fueled by Ramen",
                "urlCancion": "https://poomsc.blob.core.windows.net/canciones/04%20-%20Midwest%20Indigo.mp3",
                "urlPortada": "https://preview.redd.it/clancy-decals-at-school-v0-rxejcn71c11d1.jpg?width=320&format=pjpg&auto=webp&s=9282940783035a0d13036f235453368382f43af2",
                "anio": 2000,
                "edicion": "Original"
            },
            {
                "artistas": "Twenty One Pilots",
                "precio": 0,
                "tipoMultimedia": "Cancion",
                "formato": "Digital",
                "generos": "Generos default",
                "titulo": "Vignette",
                "duracion": 0,
                "selloDiscografico": "Fueled by Ramen",
                "urlCancion": "https://poomsc.blob.core.windows.net/canciones/06%20-%20Vignette.mp3",
                "urlPortada": "https://preview.redd.it/clancy-decals-at-school-v0-rxejcn71c11d1.jpg?width=320&format=pjpg&auto=webp&s=9282940783035a0d13036f235453368382f43af2",
                "anio": 2000,
                "edicion": "Original"
            },
            {
                "artistas": "Twenty One Pilots",
                "precio": 0,
                "tipoMultimedia": "Cancion",
                "formato": "Digital",
                "generos": "Generos default",
                "titulo": "Paladin Strait",
                "duracion": 0,
                "selloDiscografico": "Fueled by Ramen",
                "urlCancion": "https://poomsc.blob.core.windows.net/canciones/13%20-%20Paladin%20Strait.mp3",
                "urlPortada": "https://preview.redd.it/clancy-decals-at-school-v0-rxejcn71c11d1.jpg?width=320&format=pjpg&auto=webp&s=9282940783035a0d13036f235453368382f43af2",
                "anio": 2000,
                "edicion": "Original"
            },
            {
                "artistas": "Twenty One Pilots",
                "precio": 0,
                "tipoMultimedia": "Cancion",
                "formato": "Digital",
                "generos": "Generos default",
                "titulo": "Backslide",
                "duracion": 0,
                "selloDiscografico": "Fueled by Ramen",
                "urlCancion": "https://poomsc.blob.core.windows.net/canciones/03%20-%20Backslide.mp3",
                "urlPortada": "https://preview.redd.it/clancy-decals-at-school-v0-rxejcn71c11d1.jpg?width=320&format=pjpg&auto=webp&s=9282940783035a0d13036f235453368382f43af2",
                "anio": 2000,
                "edicion": "Original"
            },
            {
                "artistas": "Twenty One Pilots",
                "precio": 0,
                "tipoMultimedia": "Cancion",
                "formato": "Digital",
                "generos": "Generos default",
                "titulo": "Routines in the night",
                "duracion": 0,
                "selloDiscografico": "Fueled by Ramen",
                "urlCancion": "https://poomsc.blob.core.windows.net/canciones/05%20-%20Routines%20In%20The%20Night.mp3",
                "urlPortada": "https://preview.redd.it/clancy-decals-at-school-v0-rxejcn71c11d1.jpg?width=320&format=pjpg&auto=webp&s=9282940783035a0d13036f235453368382f43af2",
                "anio": 2000,
                "edicion": "Original"
            },
            {
                "artistas": "Twenty One Pilots",
                "precio": 0,
                "tipoMultimedia": "Cancion",
                "formato": "Digital",
                "generos": "Generos default",
                "titulo": "Lavish",
                "duracion": 0,
                "selloDiscografico": "Fueled by Ramen",
                "urlCancion": "https://poomsc.blob.core.windows.net/canciones/08%20-%20Lavish.mp3",
                "urlPortada": "https://preview.redd.it/clancy-decals-at-school-v0-rxejcn71c11d1.jpg?width=320&format=pjpg&auto=webp&s=9282940783035a0d13036f235453368382f43af2",
                "anio": 2000,
                "edicion": "Original"
            },
            {
                "artistas": "Twenty One Pilots",
                "precio": 0,
                "tipoMultimedia": "Cancion",
                "formato": "Digital",
                "generos": "Generos default",
                "titulo": "Navegating",
                "duracion": 0,
                "selloDiscografico": "Fueled by Ramen",
                "urlCancion": "https://poomsc.blob.core.windows.net/canciones/09%20-%20Navigating.mp3",
                "urlPortada": "https://preview.redd.it/clancy-decals-at-school-v0-rxejcn71c11d1.jpg?width=320&format=pjpg&auto=webp&s=9282940783035a0d13036f235453368382f43af2",
                "anio": 2000,
                "edicion": "Original"
            },
            {
                "artistas": "Twenty One Pilots",
                "precio": 0,
                "tipoMultimedia": "Cancion",
                "formato": "Digital",
                "generos": "Generos default",
                "titulo": "Snap back",
                "duracion": 0,
                "selloDiscografico": "Fueled by Ramen",
                "urlCancion": "https://poomsc.blob.core.windows.net/canciones/10%20-%20Snap%20Back.mp3",
                "urlPortada": "https://preview.redd.it/clancy-decals-at-school-v0-rxejcn71c11d1.jpg?width=320&format=pjpg&auto=webp&s=9282940783035a0d13036f235453368382f43af2",
                "anio": 2000,
                "edicion": "Original"
            },
            {
                "artistas": "Twenty One Pilots",
                "precio": 0,
                "tipoMultimedia": "Cancion",
                "formato": "Digital",
                "generos": "Generos default",
                "titulo": "Oldies station",
                "duracion": 0,
                "selloDiscografico": "Fueled by Ramen",
                "urlCancion": "https://poomsc.blob.core.windows.net/canciones/11%20-%20Oldies%20Station.mp3",
                "urlPortada": "https://preview.redd.it/clancy-decals-at-school-v0-rxejcn71c11d1.jpg?width=320&format=pjpg&auto=webp&s=9282940783035a0d13036f235453368382f43af2",
                "anio": 2000,
                "edicion": "Original"
            },
            {
                "artistas": "Twenty One Pilots",
                "precio": 0,
                "tipoMultimedia": "Cancion",
                "formato": "Digital",
                "generos": "Generos default",
                "titulo": "At the risk of a feeling dumb",
                "duracion": 0,
                "selloDiscografico": "Fueled by Ramen",
                "urlCancion": "https://poomsc.blob.core.windows.net/canciones/12%20-%20At%20The%20Risk%20Of%20Feeling%20Dumb.mp3",
                "urlPortada": "https://preview.redd.it/clancy-decals-at-school-v0-rxejcn71c11d1.jpg?width=320&format=pjpg&auto=webp&s=9282940783035a0d13036f235453368382f43af2",
                "anio": 2000,
                "edicion": "Original"
            }
        ],
        "listaEnlacesDescarga": [
            {
                "enlaceGenerado": "https://poomsc.blob.core.windows.net/canciones/01%20-%20Overcompensate.mp3?sv=2024-05-04&se=2025-07-01T07%3A12%3A47Z&sr=b&sp=r&sig=hX2plcab%2FFFoN2svOZqZ%2BITqk40EvD2NP0zIK1B3iaA%3D",
                "estadoDescarga": false,
                "fechaExpiracion": "2025-07-08T01:07:47",
                "fechaGeneracion": "2025-07-01T01:07:47",
                "fechaDescarga": null,
                "estadoPenalizacion": false
            },
            {
                "enlaceGenerado": "https://poomsc.blob.core.windows.net/canciones/02%20-%20Next%20Semester.mp3?sv=2024-05-04&se=2025-07-01T07%3A12%3A47Z&sr=b&sp=r&sig=yVm%2FDtndQlIl5%2BntrUHGSih%2FxVlb39IVmlxhvEkTpT0%3D",
                "estadoDescarga": false,
                "fechaExpiracion": "2025-07-08T01:07:47",
                "fechaGeneracion": "2025-07-01T01:07:47",
                "fechaDescarga": null,
                "estadoPenalizacion": false
            },
            {
                "enlaceGenerado": "https://poomsc.blob.core.windows.net/canciones/04%20-%20Midwest%20Indigo.mp3?sv=2024-05-04&se=2025-07-01T07%3A12%3A47Z&sr=b&sp=r&sig=XsPkXaqrAg7PsoxcqGZTz53VHKsshQ7Dd8%2Bjisj2sQE%3D",
                "estadoDescarga": false,
                "fechaExpiracion": "2025-07-08T01:07:47",
                "fechaGeneracion": "2025-07-01T01:07:47",
                "fechaDescarga": null,
                "estadoPenalizacion": false
            },
            {
                "enlaceGenerado": "https://poomsc.blob.core.windows.net/canciones/06%20-%20Vignette.mp3?sv=2024-05-04&se=2025-07-01T07%3A12%3A47Z&sr=b&sp=r&sig=ddYhJwMfJWpKR9mNEmFL1h5m9oZ4LFzS2edAv8zfkBg%3D",
                "estadoDescarga": false,
                "fechaExpiracion": "2025-07-08T01:07:47",
                "fechaGeneracion": "2025-07-01T01:07:47",
                "fechaDescarga": null,
                "estadoPenalizacion": false
            },
            {
                "enlaceGenerado": "https://poomsc.blob.core.windows.net/canciones/13%20-%20Paladin%20Strait.mp3?sv=2024-05-04&se=2025-07-01T07%3A12%3A47Z&sr=b&sp=r&sig=Bz%2FzSoELOuQxibw%2FDwTZZOGEUnAaq7Fsu6hTuFUpvdg%3D",
                "estadoDescarga": false,
                "fechaExpiracion": "2025-07-08T01:07:47",
                "fechaGeneracion": "2025-07-01T01:07:47",
                "fechaDescarga": null,
                "estadoPenalizacion": false
            },
            {
                "enlaceGenerado": "https://poomsc.blob.core.windows.net/canciones/03%20-%20Backslide.mp3?sv=2024-05-04&se=2025-07-01T07%3A12%3A47Z&sr=b&sp=r&sig=xTOxfItU6E6GtDsUJFvyAjVq7ClwthgNa63rP6ARDdc%3D",
                "estadoDescarga": false,
                "fechaExpiracion": "2025-07-08T01:07:47",
                "fechaGeneracion": "2025-07-01T01:07:47",
                "fechaDescarga": null,
                "estadoPenalizacion": false
            },
            {
                "enlaceGenerado": "https://poomsc.blob.core.windows.net/canciones/05%20-%20Routines%20In%20The%20Night.mp3?sv=2024-05-04&se=2025-07-01T07%3A12%3A47Z&sr=b&sp=r&sig=cCqGrk%2BxFN1Onq6fXXQcDMcxuwZQDgiouMG0tKhqdbs%3D",
                "estadoDescarga": false,
                "fechaExpiracion": "2025-07-08T01:07:47",
                "fechaGeneracion": "2025-07-01T01:07:47",
                "fechaDescarga": null,
                "estadoPenalizacion": false
            },
            {
                "enlaceGenerado": "https://poomsc.blob.core.windows.net/canciones/08%20-%20Lavish.mp3?sv=2024-05-04&se=2025-07-01T07%3A12%3A47Z&sr=b&sp=r&sig=Hc2tS5PsactG3YXEQXI4ehxJNIpJzTr3tTAk4Mo9R7k%3D",
                "estadoDescarga": false,
                "fechaExpiracion": "2025-07-08T01:07:47",
                "fechaGeneracion": "2025-07-01T01:07:47",
                "fechaDescarga": null,
                "estadoPenalizacion": false
            },
            {
                "enlaceGenerado": "https://poomsc.blob.core.windows.net/canciones/09%20-%20Navigating.mp3?sv=2024-05-04&se=2025-07-01T07%3A12%3A47Z&sr=b&sp=r&sig=jdcaef93eoXjNJhY3Hmx%2BiashD8NMh5zJkHCMDI9UD0%3D",
                "estadoDescarga": false,
                "fechaExpiracion": "2025-07-08T01:07:47",
                "fechaGeneracion": "2025-07-01T01:07:47",
                "fechaDescarga": null,
                "estadoPenalizacion": false
            },
            {
                "enlaceGenerado": "https://poomsc.blob.core.windows.net/canciones/10%20-%20Snap%20Back.mp3?sv=2024-05-04&se=2025-07-01T07%3A12%3A47Z&sr=b&sp=r&sig=Qd5smRpsCSAAVN0M3x5BNvpfygw0Nhu09OHyOaXYpkk%3D",
                "estadoDescarga": false,
                "fechaExpiracion": "2025-07-08T01:07:47",
                "fechaGeneracion": "2025-07-01T01:07:47",
                "fechaDescarga": null,
                "estadoPenalizacion": false
            },
            {
                "enlaceGenerado": "https://poomsc.blob.core.windows.net/canciones/11%20-%20Oldies%20Station.mp3?sv=2024-05-04&se=2025-07-01T07%3A12%3A47Z&sr=b&sp=r&sig=8suqbYhfSgCxzWia%2BGdSWS4ibjY%2BXBVzN2Tk%2BHuQUPY%3D",
                "estadoDescarga": false,
                "fechaExpiracion": "2025-07-08T01:07:47",
                "fechaGeneracion": "2025-07-01T01:07:47",
                "fechaDescarga": null,
                "estadoPenalizacion": false
            },
            {
                "enlaceGenerado": "https://poomsc.blob.core.windows.net/canciones/12%20-%20At%20The%20Risk%20Of%20Feeling%20Dumb.mp3?sv=2024-05-04&se=2025-07-01T07%3A12%3A47Z&sr=b&sp=r&sig=EjpJWMkKN5gAqbsTmwvP30sVeSzlxQrH7ZzV%2FwmFtmk%3D",
                "estadoDescarga": false,
                "fechaExpiracion": "2025-07-08T01:07:47",
                "fechaGeneracion": "2025-07-01T01:07:47",
                "fechaDescarga": null,
                "estadoPenalizacion": false
            }
        ]
    },
    {
        "fechaCompra": "2025-07-01T01:12:08",
        "estadoCompra": true,
        "correoUsuario": "Jheromscript@gmail.com",
        "codigoCompra": "CDC000002",
        "contenidoComprado": [
            {
                "artistas": "DEFTONES",
                "precio": 0,
                "tipoMultimedia": "Cancion",
                "formato": "DIGITAL",
                "generos": "Generos default",
                "titulo": "BACK TO SCHOOL",
                "duracion": 0,
                "selloDiscografico": "MAVERIK",
                "urlCancion": "https://poomsc.blob.core.windows.net/canciones/08%20Sextape.mp3",
                "urlPortada": "https://akamai.sscdn.co/uploadfile/letras/albuns/a/4/8/f/46481684259853.jpg",
                "anio": 2000,
                "edicion": "ORIGINAL"
            },
            {
                "artistas": "DEFTONES",
                "precio": 0,
                "tipoMultimedia": "Cancion",
                "formato": "DIGITAL",
                "generos": "Generos default",
                "titulo": "FEITICEIRA",
                "duracion": 0,
                "selloDiscografico": "MAVERIK",
                "urlCancion": "https://poomsc.blob.core.windows.net/canciones/01%20-%20Deftones%20-%20Feiticeira.mp3",
                "urlPortada": "https://akamai.sscdn.co/uploadfile/letras/albuns/a/4/8/f/46481684259853.jpg",
                "anio": 2000,
                "edicion": "ORIGINAL"
            },
            {
                "artistas": "DEFTONES",
                "precio": 0,
                "tipoMultimedia": "Cancion",
                "formato": "DIGITAL",
                "generos": "Generos default",
                "titulo": "DIGITAL BATH",
                "duracion": 0,
                "selloDiscografico": "MAVERIK",
                "urlCancion": "https://poomsc.blob.core.windows.net/canciones/02%20-%20Deftones%20-%20Digital%20Bath.mp3",
                "urlPortada": "https://akamai.sscdn.co/uploadfile/letras/albuns/a/4/8/f/46481684259853.jpg",
                "anio": 2000,
                "edicion": "ORIGINAL"
            },
            {
                "artistas": "DEFTONES",
                "precio": 0,
                "tipoMultimedia": "Cancion",
                "formato": "DIGITAL",
                "generos": "Generos default",
                "titulo": "ELITE",
                "duracion": 0,
                "selloDiscografico": "MAVERIK",
                "urlCancion": "https://poomsc.blob.core.windows.net/canciones/03%20-%20Deftones%20-%20Elite.mp3",
                "urlPortada": "https://akamai.sscdn.co/uploadfile/letras/albuns/a/4/8/f/46481684259853.jpg",
                "anio": 2000,
                "edicion": "ORIGINAL"
            },
            {
                "artistas": "DEFTONES",
                "precio": 0,
                "tipoMultimedia": "Cancion",
                "formato": "DIGITAL",
                "generos": "Generos default",
                "titulo": "STREET CARP",
                "duracion": 0,
                "selloDiscografico": "MAVERIK",
                "urlCancion": "https://poomsc.blob.core.windows.net/canciones/05%20-%20Deftones%20-%20Street%20Carp.mp3",
                "urlPortada": "https://akamai.sscdn.co/uploadfile/letras/albuns/a/4/8/f/46481684259853.jpg",
                "anio": 2000,
                "edicion": "ORIGINAL"
            },
            {
                "artistas": "DEFTONES",
                "precio": 0,
                "tipoMultimedia": "Cancion",
                "formato": "DIGITAL",
                "generos": "Generos default",
                "titulo": "TEENAGER",
                "duracion": 0,
                "selloDiscografico": "MAVERIK",
                "urlCancion": "https://poomsc.blob.core.windows.net/canciones/06%20-%20Deftones%20-%20Teenager.mp3",
                "urlPortada": "https://akamai.sscdn.co/uploadfile/letras/albuns/a/4/8/f/46481684259853.jpg",
                "anio": 2000,
                "edicion": "ORIGINAL"
            },
            {
                "artistas": "DEFTONES",
                "precio": 0,
                "tipoMultimedia": "Cancion",
                "formato": "DIGITAL",
                "generos": "Generos default",
                "titulo": "KNIFE PRTY",
                "duracion": 0,
                "selloDiscografico": "MAVERIK",
                "urlCancion": "https://poomsc.blob.core.windows.net/canciones/07%20-%20Deftones%20-%20Knife%20Party.mp3",
                "urlPortada": "https://akamai.sscdn.co/uploadfile/letras/albuns/a/4/8/f/46481684259853.jpg",
                "anio": 2000,
                "edicion": "ORIGINAL"
            },
            {
                "artistas": "DEFTONES",
                "precio": 0,
                "tipoMultimedia": "Cancion",
                "formato": "DIGITAL",
                "generos": "Generos default",
                "titulo": "KOREA",
                "duracion": 0,
                "selloDiscografico": "MAVERIK",
                "urlCancion": "https://poomsc.blob.core.windows.net/canciones/08%20-%20Deftones%20-%20Korea.mp3",
                "urlPortada": "https://akamai.sscdn.co/uploadfile/letras/albuns/a/4/8/f/46481684259853.jpg",
                "anio": 2000,
                "edicion": "ORIGINAL"
            },
            {
                "artistas": "DEFTONES",
                "precio": 0,
                "tipoMultimedia": "Cancion",
                "formato": "DIGITAL",
                "generos": "Generos default",
                "titulo": "PASSENGER",
                "duracion": 0,
                "selloDiscografico": "MAVERIK",
                "urlCancion": "https://poomsc.blob.core.windows.net/canciones/09%20-%20Deftones%20-%20Passenger.mp3",
                "urlPortada": "https://akamai.sscdn.co/uploadfile/letras/albuns/a/4/8/f/46481684259853.jpg",
                "anio": 2000,
                "edicion": "ORIGINAL"
            },
            {
                "artistas": "DEFTONES",
                "precio": 0,
                "tipoMultimedia": "Cancion",
                "formato": "DIGITAL",
                "generos": "Generos default",
                "titulo": "CHANGE",
                "duracion": 0,
                "selloDiscografico": "MAVERIK",
                "urlCancion": "https://poomsc.blob.core.windows.net/canciones/10%20-%20Deftones%20-%20Change%20(In%20The%20House%20Of%20Flies).mp3",
                "urlPortada": "https://akamai.sscdn.co/uploadfile/letras/albuns/a/4/8/f/46481684259853.jpg",
                "anio": 2000,
                "edicion": "ORIGINAL"
            },
            {
                "artistas": "DEFTONES",
                "precio": 0,
                "tipoMultimedia": "Cancion",
                "formato": "DIGITAL",
                "generos": "Generos default",
                "titulo": "PINK MAGGIT",
                "duracion": 0,
                "selloDiscografico": "MAVERIK",
                "urlCancion": "https://poomsc.blob.core.windows.net/canciones/11%20-%20Deftones%20-%20Pink%20Maggit.mp3",
                "urlPortada": "https://akamai.sscdn.co/uploadfile/letras/albuns/a/4/8/f/46481684259853.jpg",
                "anio": 2000,
                "edicion": "ORIGINAL"
            },
            {
                "artistas": "DEFTONES",
                "precio": 0,
                "tipoMultimedia": "Cancion",
                "formato": "DIGITAL",
                "generos": "Generos default",
                "titulo": "RX QUEEN",
                "duracion": 0,
                "selloDiscografico": "MAVERIK",
                "urlCancion": "https://poomsc.blob.core.windows.net/canciones/04%20-%20Deftones%20-%20RX%20Queen.mp3",
                "urlPortada": "https://akamai.sscdn.co/uploadfile/letras/albuns/a/4/8/f/46481684259853.jpg",
                "anio": 2000,
                "edicion": "ORIGINAL"
            }
        ],
        "listaEnlacesDescarga": [
            {
                "enlaceGenerado": "https://poomsc.blob.core.windows.net/canciones/08%20Sextape.mp3?sv=2024-05-04&se=2025-07-01T07%3A17%3A08Z&sr=b&sp=r&sig=fnWuQdPzgYhYKya5TkjAcHVusyvGszIOqCyy7oxrD54%3D",
                "estadoDescarga": false,
                "fechaExpiracion": "2025-07-08T01:12:08",
                "fechaGeneracion": "2025-07-01T01:12:08",
                "fechaDescarga": null,
                "estadoPenalizacion": false
            },
            {
                "enlaceGenerado": "https://poomsc.blob.core.windows.net/canciones/01%20-%20Deftones%20-%20Feiticeira.mp3?sv=2024-05-04&se=2025-07-01T07%3A17%3A08Z&sr=b&sp=r&sig=yRdswSgjqArileSy3qGMjSiy%2Bo8DNTmtW3rD%2B9B0w1M%3D",
                "estadoDescarga": false,
                "fechaExpiracion": "2025-07-08T01:12:08",
                "fechaGeneracion": "2025-07-01T01:12:08",
                "fechaDescarga": null,
                "estadoPenalizacion": false
            },
            {
                "enlaceGenerado": "https://poomsc.blob.core.windows.net/canciones/02%20-%20Deftones%20-%20Digital%20Bath.mp3?sv=2024-05-04&se=2025-07-01T07%3A17%3A08Z&sr=b&sp=r&sig=U0VR%2BCUkOF9YAImv9aPBs3ArKs3D2YudSPdMhhL9rL0%3D",
                "estadoDescarga": false,
                "fechaExpiracion": "2025-07-08T01:12:08",
                "fechaGeneracion": "2025-07-01T01:12:08",
                "fechaDescarga": null,
                "estadoPenalizacion": false
            },
            {
                "enlaceGenerado": "https://poomsc.blob.core.windows.net/canciones/03%20-%20Deftones%20-%20Elite.mp3?sv=2024-05-04&se=2025-07-01T07%3A17%3A08Z&sr=b&sp=r&sig=XLIjw8qwYkDSRFArEPNBeJ4dhEQ7adIed6VArOsNtgM%3D",
                "estadoDescarga": false,
                "fechaExpiracion": "2025-07-08T01:12:08",
                "fechaGeneracion": "2025-07-01T01:12:08",
                "fechaDescarga": null,
                "estadoPenalizacion": false
            },
            {
                "enlaceGenerado": "https://poomsc.blob.core.windows.net/canciones/05%20-%20Deftones%20-%20Street%20Carp.mp3?sv=2024-05-04&se=2025-07-01T07%3A17%3A08Z&sr=b&sp=r&sig=w%2FvnEYZhtree3dLFmtU22zEF5etTAE0ditlglexq%2BFE%3D",
                "estadoDescarga": false,
                "fechaExpiracion": "2025-07-08T01:12:08",
                "fechaGeneracion": "2025-07-01T01:12:08",
                "fechaDescarga": null,
                "estadoPenalizacion": false
            },
            {
                "enlaceGenerado": "https://poomsc.blob.core.windows.net/canciones/06%20-%20Deftones%20-%20Teenager.mp3?sv=2024-05-04&se=2025-07-01T07%3A17%3A08Z&sr=b&sp=r&sig=IQmnZtLI1bxKXwZGHzVxLMO41XO%2F01f4TWWB%2BU0j%2FXU%3D",
                "estadoDescarga": false,
                "fechaExpiracion": "2025-07-08T01:12:08",
                "fechaGeneracion": "2025-07-01T01:12:08",
                "fechaDescarga": null,
                "estadoPenalizacion": false
            },
            {
                "enlaceGenerado": "https://poomsc.blob.core.windows.net/canciones/07%20-%20Deftones%20-%20Knife%20Party.mp3?sv=2024-05-04&se=2025-07-01T07%3A17%3A08Z&sr=b&sp=r&sig=6XggFDMKU8Kz7LVF5F4TgvgLo3V7e1wGlN33a%2B9Ds%2Bg%3D",
                "estadoDescarga": false,
                "fechaExpiracion": "2025-07-08T01:12:08",
                "fechaGeneracion": "2025-07-01T01:12:08",
                "fechaDescarga": null,
                "estadoPenalizacion": false
            },
            {
                "enlaceGenerado": "https://poomsc.blob.core.windows.net/canciones/08%20-%20Deftones%20-%20Korea.mp3?sv=2024-05-04&se=2025-07-01T07%3A17%3A08Z&sr=b&sp=r&sig=f6FxBqY0ojv%2BBjLrkinMLfTq2sMZlot5L1mlFCKOqm0%3D",
                "estadoDescarga": false,
                "fechaExpiracion": "2025-07-08T01:12:08",
                "fechaGeneracion": "2025-07-01T01:12:08",
                "fechaDescarga": null,
                "estadoPenalizacion": false
            },
            {
                "enlaceGenerado": "https://poomsc.blob.core.windows.net/canciones/09%20-%20Deftones%20-%20Passenger.mp3?sv=2024-05-04&se=2025-07-01T07%3A17%3A08Z&sr=b&sp=r&sig=eQoPVqtnX5t8Cujr%2BaazPyHdUY6TSnPbmrV57%2BNQJdA%3D",
                "estadoDescarga": false,
                "fechaExpiracion": "2025-07-08T01:12:08",
                "fechaGeneracion": "2025-07-01T01:12:08",
                "fechaDescarga": null,
                "estadoPenalizacion": false
            },
            {
                "enlaceGenerado": "https://poomsc.blob.core.windows.net/canciones/10%20-%20Deftones%20-%20Change%20%28In%20The%20House%20Of%20Flies%29.mp3?sv=2024-05-04&se=2025-07-01T07%3A17%3A08Z&sr=b&sp=r&sig=xzd1LBh2JEk7xYtuhGfawVsI3Aozae4pxMXBQUcTBZs%3D",
                "estadoDescarga": false,
                "fechaExpiracion": "2025-07-08T01:12:08",
                "fechaGeneracion": "2025-07-01T01:12:08",
                "fechaDescarga": null,
                "estadoPenalizacion": false
            },
            {
                "enlaceGenerado": "https://poomsc.blob.core.windows.net/canciones/11%20-%20Deftones%20-%20Pink%20Maggit.mp3?sv=2024-05-04&se=2025-07-01T07%3A17%3A08Z&sr=b&sp=r&sig=PfEELWdAC%2FFHXq97Pbx71HL55XyvkrU5VNejybs5sh8%3D",
                "estadoDescarga": false,
                "fechaExpiracion": "2025-07-08T01:12:08",
                "fechaGeneracion": "2025-07-01T01:12:08",
                "fechaDescarga": null,
                "estadoPenalizacion": false
            },
            {
                "enlaceGenerado": "https://poomsc.blob.core.windows.net/canciones/04%20-%20Deftones%20-%20RX%20Queen.mp3?sv=2024-05-04&se=2025-07-01T07%3A17%3A08Z&sr=b&sp=r&sig=GeQyVyqRGh04UZM%2BDfjS0b%2B4iFBMLgQOpoQUzkUKhNs%3D",
                "estadoDescarga": false,
                "fechaExpiracion": "2025-07-08T01:12:08",
                "fechaGeneracion": "2025-07-01T01:12:08",
                "fechaDescarga": null,
                "estadoPenalizacion": false
            }
        ]
    },
    {
        "fechaCompra": "2025-07-01T01:13:20",
        "estadoCompra": true,
        "correoUsuario": "Jheromscript@gmail.com",
        "codigoCompra": "CDC000001",
        "contenidoComprado": [
            {
                "artistas": "Deftones",
                "precio": 0,
                "tipoMultimedia": "Cancion",
                "formato": "Digital",
                "generos": "Generos default",
                "titulo": "Diamond Eyes",
                "duracion": 0,
                "selloDiscografico": "Reprise Records",
                "urlCancion": "https://poomsc.blob.core.windows.net/canciones/01%20Diamond%20Eyes.mp3",
                "urlPortada": "https://upload.wikimedia.org/wikipedia/en/8/8b/Deftones_-_Diamond_Eyes.jpg",
                "anio": 2000,
                "edicion": "Original"
            },
            {
                "artistas": "Deftones",
                "precio": 0,
                "tipoMultimedia": "Cancion",
                "formato": "Digital",
                "generos": "Generos default",
                "titulo": "Royal",
                "duracion": 0,
                "selloDiscografico": "Reprise Records",
                "urlCancion": "https://poomsc.blob.core.windows.net/canciones/02%20Royal.mp3",
                "urlPortada": "https://upload.wikimedia.org/wikipedia/en/8/8b/Deftones_-_Diamond_Eyes.jpg",
                "anio": 2000,
                "edicion": "Original"
            },
            {
                "artistas": "Deftones",
                "precio": 0,
                "tipoMultimedia": "Cancion",
                "formato": "Digital",
                "generos": "Generos default",
                "titulo": "CMND-CTRL",
                "duracion": 0,
                "selloDiscografico": "Reprise Records",
                "urlCancion": "https://poomsc.blob.core.windows.net/canciones/03%20CMND-CTRL.mp3",
                "urlPortada": "https://upload.wikimedia.org/wikipedia/en/8/8b/Deftones_-_Diamond_Eyes.jpg",
                "anio": 2000,
                "edicion": "Original"
            },
            {
                "artistas": "Deftones",
                "precio": 0,
                "tipoMultimedia": "Cancion",
                "formato": "Digital",
                "generos": "Generos default",
                "titulo": "Youve Seen The Butcher",
                "duracion": 0,
                "selloDiscografico": "Reprise Records",
                "urlCancion": "https://poomsc.blob.core.windows.net/canciones/04%20You've%20Seen%20The%20Butcher.mp3",
                "urlPortada": "https://upload.wikimedia.org/wikipedia/en/8/8b/Deftones_-_Diamond_Eyes.jpg",
                "anio": 2000,
                "edicion": "Original"
            },
            {
                "artistas": "Deftones",
                "precio": 0,
                "tipoMultimedia": "Cancion",
                "formato": "Digital",
                "generos": "Generos default",
                "titulo": "Beauty School",
                "duracion": 0,
                "selloDiscografico": "Reprise Records",
                "urlCancion": "https://poomsc.blob.core.windows.net/canciones/05%20Beauty%20School.mp3",
                "urlPortada": "https://upload.wikimedia.org/wikipedia/en/8/8b/Deftones_-_Diamond_Eyes.jpg",
                "anio": 2000,
                "edicion": "Original"
            },
            {
                "artistas": "Deftones",
                "precio": 0,
                "tipoMultimedia": "Cancion",
                "formato": "Digital",
                "generos": "Generos default",
                "titulo": "Prince",
                "duracion": 0,
                "selloDiscografico": "Reprise Records",
                "urlCancion": "https://poomsc.blob.core.windows.net/canciones/06%20Prince.mp3",
                "urlPortada": "https://upload.wikimedia.org/wikipedia/en/8/8b/Deftones_-_Diamond_Eyes.jpg",
                "anio": 2000,
                "edicion": "Original"
            },
            {
                "artistas": "Deftones",
                "precio": 0,
                "tipoMultimedia": "Cancion",
                "formato": "Digital",
                "generos": "Generos default",
                "titulo": "Rocket Skates",
                "duracion": 0,
                "selloDiscografico": "Reprise Records",
                "urlCancion": "https://poomsc.blob.core.windows.net/canciones/07%20Rocket%20Skates.mp3",
                "urlPortada": "https://upload.wikimedia.org/wikipedia/en/8/8b/Deftones_-_Diamond_Eyes.jpg",
                "anio": 2000,
                "edicion": "Original"
            },
            {
                "artistas": "Deftones",
                "precio": 0,
                "tipoMultimedia": "Cancion",
                "formato": "Digital",
                "generos": "Generos default",
                "titulo": "Sextape",
                "duracion": 0,
                "selloDiscografico": "Reprise Records",
                "urlCancion": "https://poomsc.blob.core.windows.net/canciones/08%20Sextape.mp3",
                "urlPortada": "https://upload.wikimedia.org/wikipedia/en/8/8b/Deftones_-_Diamond_Eyes.jpg",
                "anio": 2000,
                "edicion": "Original"
            },
            {
                "artistas": "Deftones",
                "precio": 0,
                "tipoMultimedia": "Cancion",
                "formato": "Digital",
                "generos": "Generos default",
                "titulo": "Risk",
                "duracion": 0,
                "selloDiscografico": "Reprise Records",
                "urlCancion": "https://poomsc.blob.core.windows.net/canciones/09%20Risk.mp3",
                "urlPortada": "https://upload.wikimedia.org/wikipedia/en/8/8b/Deftones_-_Diamond_Eyes.jpg",
                "anio": 2000,
                "edicion": "Original"
            },
            {
                "artistas": "Deftones",
                "precio": 0,
                "tipoMultimedia": "Cancion",
                "formato": "Digital",
                "generos": "Generos default",
                "titulo": "976-Evil",
                "duracion": 0,
                "selloDiscografico": "Reprise Records",
                "urlCancion": "https://poomsc.blob.core.windows.net/canciones/10%20976-Evil.mp3",
                "urlPortada": "https://upload.wikimedia.org/wikipedia/en/8/8b/Deftones_-_Diamond_Eyes.jpg",
                "anio": 2000,
                "edicion": "Original"
            },
            {
                "artistas": "Deftones",
                "precio": 0,
                "tipoMultimedia": "Cancion",
                "formato": "Digital",
                "generos": "Generos default",
                "titulo": "This Place Is Death",
                "duracion": 0,
                "selloDiscografico": "Reprise Records",
                "urlCancion": "https://poomsc.blob.core.windows.net/canciones/11%20This%20Place%20Is%20Death.mp3",
                "urlPortada": "https://upload.wikimedia.org/wikipedia/en/8/8b/Deftones_-_Diamond_Eyes.jpg",
                "anio": 2000,
                "edicion": "Original"
            }
        ],
        "listaEnlacesDescarga": [
            {
                "enlaceGenerado": "https://poomsc.blob.core.windows.net/canciones/01%20Diamond%20Eyes.mp3?sv=2024-05-04&se=2025-07-01T07%3A18%3A21Z&sr=b&sp=r&sig=GfyZ8uXgn8s%2FnLCMWnrW9eG4wJ%2BmjK28bra4mCExcyw%3D",
                "estadoDescarga": false,
                "fechaExpiracion": "2025-07-08T01:13:21",
                "fechaGeneracion": "2025-07-01T01:13:20",
                "fechaDescarga": null,
                "estadoPenalizacion": false
            },
            {
                "enlaceGenerado": "https://poomsc.blob.core.windows.net/canciones/02%20Royal.mp3?sv=2024-05-04&se=2025-07-01T07%3A18%3A21Z&sr=b&sp=r&sig=fCxj5yovqgLz1LnlTvOD%2BAqKNQllvCpcPlwS11C1wf8%3D",
                "estadoDescarga": false,
                "fechaExpiracion": "2025-07-08T01:13:21",
                "fechaGeneracion": "2025-07-01T01:13:20",
                "fechaDescarga": null,
                "estadoPenalizacion": false
            },
            {
                "enlaceGenerado": "https://poomsc.blob.core.windows.net/canciones/03%20CMND-CTRL.mp3?sv=2024-05-04&se=2025-07-01T07%3A18%3A21Z&sr=b&sp=r&sig=%2FHtPk7bR6zEqZxqefjZOCiK1ql1brBTSkQMKkDnn92c%3D",
                "estadoDescarga": false,
                "fechaExpiracion": "2025-07-08T01:13:21",
                "fechaGeneracion": "2025-07-01T01:13:20",
                "fechaDescarga": null,
                "estadoPenalizacion": false
            },
            {
                "enlaceGenerado": "https://poomsc.blob.core.windows.net/canciones/04%20You%27ve%20Seen%20The%20Butcher.mp3?sv=2024-05-04&se=2025-07-01T07%3A18%3A21Z&sr=b&sp=r&sig=6O0WfYW5xdlmZycp0PsK7MbKDV9Dic3bjOqN3pIWR0I%3D",
                "estadoDescarga": false,
                "fechaExpiracion": "2025-07-08T01:13:21",
                "fechaGeneracion": "2025-07-01T01:13:20",
                "fechaDescarga": null,
                "estadoPenalizacion": false
            },
            {
                "enlaceGenerado": "https://poomsc.blob.core.windows.net/canciones/05%20Beauty%20School.mp3?sv=2024-05-04&se=2025-07-01T07%3A18%3A21Z&sr=b&sp=r&sig=ljut1VuMX%2FyiIbihkpW3J00lr1UPbFJA4tnWmNyj5s8%3D",
                "estadoDescarga": false,
                "fechaExpiracion": "2025-07-08T01:13:21",
                "fechaGeneracion": "2025-07-01T01:13:20",
                "fechaDescarga": null,
                "estadoPenalizacion": false
            },
            {
                "enlaceGenerado": "https://poomsc.blob.core.windows.net/canciones/06%20Prince.mp3?sv=2024-05-04&se=2025-07-01T07%3A18%3A21Z&sr=b&sp=r&sig=r4S916Id439s2TUrdE1I%2F50ewpT4oF5HX2kwa7Fk%2FvU%3D",
                "estadoDescarga": false,
                "fechaExpiracion": "2025-07-08T01:13:21",
                "fechaGeneracion": "2025-07-01T01:13:20",
                "fechaDescarga": null,
                "estadoPenalizacion": false
            },
            {
                "enlaceGenerado": "https://poomsc.blob.core.windows.net/canciones/07%20Rocket%20Skates.mp3?sv=2024-05-04&se=2025-07-01T07%3A18%3A21Z&sr=b&sp=r&sig=gibHSmzxt9gBzrQBhBEe0xShqAmiMTo7xSV3q7RtHEg%3D",
                "estadoDescarga": false,
                "fechaExpiracion": "2025-07-08T01:13:21",
                "fechaGeneracion": "2025-07-01T01:13:20",
                "fechaDescarga": null,
                "estadoPenalizacion": false
            },
            {
                "enlaceGenerado": "https://poomsc.blob.core.windows.net/canciones/08%20Sextape.mp3?sv=2024-05-04&se=2025-07-01T07%3A18%3A21Z&sr=b&sp=r&sig=j50eMnGlCTKRzMWyS7uNWmGEnkGEqTZRP2LG%2FBHwMck%3D",
                "estadoDescarga": false,
                "fechaExpiracion": "2025-07-08T01:13:21",
                "fechaGeneracion": "2025-07-01T01:13:20",
                "fechaDescarga": null,
                "estadoPenalizacion": false
            },
            {
                "enlaceGenerado": "https://poomsc.blob.core.windows.net/canciones/09%20Risk.mp3?sv=2024-05-04&se=2025-07-01T07%3A18%3A21Z&sr=b&sp=r&sig=51sUBKVucvT3tWiS15pWXLqkl6l6QWGEz%2F101R6KHjs%3D",
                "estadoDescarga": false,
                "fechaExpiracion": "2025-07-08T01:13:21",
                "fechaGeneracion": "2025-07-01T01:13:20",
                "fechaDescarga": null,
                "estadoPenalizacion": false
            },
            {
                "enlaceGenerado": "https://poomsc.blob.core.windows.net/canciones/10%20976-Evil.mp3?sv=2024-05-04&se=2025-07-01T07%3A18%3A21Z&sr=b&sp=r&sig=8hEI092bEXQX591eXSkrP2XdrJzJYdAb0AKJ8pnE8%2Fo%3D",
                "estadoDescarga": false,
                "fechaExpiracion": "2025-07-08T01:13:21",
                "fechaGeneracion": "2025-07-01T01:13:20",
                "fechaDescarga": null,
                "estadoPenalizacion": false
            },
            {
                "enlaceGenerado": "https://poomsc.blob.core.windows.net/canciones/11%20This%20Place%20Is%20Death.mp3?sv=2024-05-04&se=2025-07-01T07%3A18%3A21Z&sr=b&sp=r&sig=nO3F4Ilq9awZ4rrJwlcNKYwteafthXjVRwTpBRUxx9M%3D",
                "estadoDescarga": false,
                "fechaExpiracion": "2025-07-08T01:13:21",
                "fechaGeneracion": "2025-07-01T01:13:20",
                "fechaDescarga": null,
                "estadoPenalizacion": false
            }
        ]
    },
    {
        "fechaCompra": "2025-07-01T01:14:40",
        "estadoCompra": true,
        "correoUsuario": "Jheromscript@gmail.com",
        "codigoCompra": "CDC000001",
        "contenidoComprado": [{
            "artistas": "Twenty One Pilots",
            "precio": 0,
            "tipoMultimedia": "Cancion",
            "formato": "Digital",
            "generos": "Generos default",
            "titulo": "Overcompensate",
            "duracion": 0,
            "selloDiscografico": "Fueled by Ramen",
            "urlCancion": "https://poomsc.blob.core.windows.net/canciones/01%20-%20Overcompensate.mp3",
            "urlPortada": "https://preview.redd.it/clancy-decals-at-school-v0-rxejcn71c11d1.jpg?width=320&format=pjpg&auto=webp&s=9282940783035a0d13036f235453368382f43af2",
            "anio": 2000,
            "edicion": "Original"
        }],
        "listaEnlacesDescarga": [{
            "enlaceGenerado": "https://poomsc.blob.core.windows.net/canciones/01%20-%20Overcompensate.mp3?sv=2024-05-04&se=2025-07-01T07%3A19%3A40Z&sr=b&sp=r&sig=tSoB6Ttpopzg68xg7XLuUozb6Dr9ma5HLvsEU95qvRI%3D",
            "estadoDescarga": false,
            "fechaExpiracion": "2025-07-08T01:14:40",
            "fechaGeneracion": "2025-07-01T01:14:40",
            "fechaDescarga": null,
            "estadoPenalizacion": false
        }]
    }
]